dpy_peper/__init__.py
dpy_peper/main.py
dpy_peper-1.0.1.dist-info/LICENSE
dpy_peper-1.0.1.dist-info/METADATA
dpy_peper-1.0.1.dist-info/WHEEL
dpy_peper-1.0.1.dist-info/top_level.txt
dpy_peper-1.0.1.dist-info/RECORD
