Metadata-Version: 2.1
Name: dpy-peper
Version: 1.0.1
Summary: Helper of discord.py's on_voice_state_update
Home-page: https://github.com/sevenc-nanashi/dpy_voice_helper
Author: sevenc-nanashi
Author-email: sevenc-nanashi@sevenbot.jp
License: UNKNOWN
Platform: UNKNOWN
Classifier: Programming Language :: Python :: 3.9
Classifier: License :: OSI Approved :: MIT License
Classifier: Operating System :: OS Independent
Requires-Dist: discord.py (>1.0.0<2.0.0)
